datoma-1.0.3.dist-info/METADATA
datoma-1.0.3.dist-info/WHEEL
datoma-1.0.3.dist-info/entry_points.txt
datoma/AppSyncClient.py
datoma/CustomCredentialProvider.py
datoma/DatomaJob.py
datoma/DatomaWorkflow.py
datoma/__init__.py
datoma/__main__.py
datoma/transfer_manager.py
datoma/utils.py
datoma-1.0.3.dist-info/RECORD
