Metadata-Version: 2.1
Name: datoma
Version: 1.0.3
Summary: Library to create, submit and handle Datoma's jobs and workflows from Python
License: MIT
Project-URL: Homepage, https://datoma.cloud
Project-URL: Documentation, https://datoma.readthedocs.io/en/latest/index.html#
Requires-Python: >=3.11
Requires-Dist: requests>=2.31.0
Requires-Dist: boto3>=1.29.0
Requires-Dist: requests-aws4auth>=1.2.3
Requires-Dist: gql>=3.4.1
Requires-Dist: awscrt>=0.19.13
Requires-Dist: botocore>=1.32.0
Requires-Dist: pyyaml>=6.0
Requires-Dist: websockets>=12.0
Requires-Dist: requests_toolbelt>=1.0.0
Requires-Dist: pycognito>=2023.5.0
Requires-Dist: pwinput>=1.0.3
Requires-Dist: jsonpickle>=3.0.2
